Workbook
Name valuevx: 42.314159
Name vertex42_copyright: "© 2011-2014 Vertex42 LLC"
Name vertex42_id: "work-order-template.xlsx"
Name vertex42_title: "Work Order Form Template"

Sheet Job_Order
K1: Form 1/3
J2: JOB ORDER NO.
B4: Hontech Auto Center
B5: 70 Bayan Bayanan Ave cor Narra St. | J5: DATE:
B6: Marikina Heights, Marikina City
B7: fb.com/hontechautocenter
B8: 85644550/ 71219124/ 09458757441/ 09525065084- VIBER
B9: CUSTOMER DETAILS
B10: Name : | G10: Year/Model : | J10: Plate No :
B11: Address : | G11: KM Reading : | J11: Intake Date :
B12: Contact No. : | G12: Engine No : | J12: Promise Date :
B13: E-Mail Add. : | G13: Chassis No. : | J13: Color :
B16: CUSTOMER'S DESCRIPTION OF REQUESTED SERVICE/CONCERN (To be filled out by Service Advisor)
B18: NOTE: To avail of the warranty given for material, parts, and service, owner supplied is discouraged, otherwise a surcharge of 25% of the price of item is automatically applied. The cost of the item/s shall be the current price of Hontech Auto Center, Inc.
B19: Interviewed by:
C20: Service Advisor
B21: AUTHORIZATION
B22: I hereby authorize you and your assigned employees to operate the vehicle for purposes of testing, inspection, pick-up or delivery.
D23: =C10
D24: Customer Name and Signature
B25: DIAGNOSTIC RESULT | D25: PARTS | H25: MATERIALS
D26: DESCRIPTION | E26: QTY | F26: UNIT PRICE | G26: AMOUNT | H26: DESCRIPTION | I26: QTY | J26: UNIT PRICE | K26: AMOUNT
G27: =E27*F27 | K27: =I27*J27
G28: =E28*F28 | K28: =I28*J28
G29: =E29*F29 | K29: =I29*J29
G30: =E30*F30 | K30: =I30*J30
G31: =E31*F31 | K31: =I31*J31
G32: =E32*F32 | K32: =I32*J32
G33: =E33*F33 | K33: =I33*J33
G34: =E34*F34 | K34: =I34*J34
G35: =E35*F35 | K35: =I35*J35
G36: =E36*F36 | K36: =I36*J36
G37: =E37*F37 | K37: =I37*J37
G38: =E38*F38 | K38: =I38*J38
... G49: =E49*F49 | K49: =I49*J49
F50: PARTS: | G50: =SUM(G27:G49) | J50: MATERIALS: | K50: =SUM(K27:K49)
J51: TOTAL
B53: Diagnosed by: | H53: Assessed by:
C54: Auto Mechanic | I54: Parts/Materials Controller
B55: CERTIFICATE OF COMPLETION/ACCEPTANCE
B56: This is to certify that the aforementioned vehicle was thoroughly inspected/checked/examined and was done in accordance with the agreed recommendation/discussions and satisfaction of the customer
C57: Recommending Approval: | H57: Approved by:
C59: Service Advisor | H59: Chief, Auto Mechanic / Authorized AM
C60: CONFORME: | H60: Concurred by:
C61: =C10
C62: Customer's Name & Signature | H62: General Manager
B64: Mahal Naming Mga Kustomer,
B65: Para sa inyong seguridad at kapakinabangan ng lahat, pinapayuhan po namin kayong kuni ang lahat ng mahahalagang gamit mula
B66: sa inyong sasakyan bago ito ipagkatiwala sa aming mga kawani. Malaki po ang maitutulong ng inyong kooperasyon upang masiguro
B67: namin ang mahusay na serbisyo.
B68: Maraming salamat po sa inyong patuloy na suporta.
B69: Ang Pamunuan
B70: Name : | C70: =C10 | G70: Plate No./Year/Model : | H70: =K10 | J70: =H10
B71: Service Advisor : | G71: Contact : | H71: 09458757441/ 09525065084- VIBER
B72: Date: | C72: =K5 | G72: Claim Stub : | H72: =K2
B74: (Please present this to our Service Advisor to claim required documents for the release of your vehicle)
B75: THANK YOU FOR TRUSTING HONTECH AUTO CENTER, INC!
H76: Hontech Auto Center, Inc
H77: 70 Bayan Bayanan Ave. cor Narra St. Marikina Heights, Marikina City
H78: Tel #: (8)564-4550/ 71219124

Sheet Quotation_No 1
H1: Form 2/3
G2: QUOTATION NO.
A3: "Building Trust"
A4: Hontech Auto Center
A5: 70 Bayan Bayanan Ave cor Narra St. | G5: DATE:
A6: Marikina Heights, Marikina City | G6: JOB ORDER NO.: | H6: =Job_Order!K2
A7: fb.com/hontechautocenter | G7: PROMISED DATE:
A8: =Job_Order!B8
A9: CUSTOMER DETAILS
A10: Name: | B10: =Job_Order!C10 | F10: Plate No: | G10: =Job_Order!K10
A11: Address: | B11: =Job_Order!C11 | F11: Year/Model: | G11: =Job_Order!H10
A12: Contact No: | B12: =Job_Order!C12 | F12: Color: | G12: =Job_Order!K13
A14: PARTS/MATERIAL | C14: QTY | D14: FRT | E14: LABOR | F14: PARTS | G14: MATERALS | H14: AMOUNT
E15: =D15*550 | H15: =E15+F15+G15
E16: =D16*550 | H16: =E16+F16+G16
E17: =D17*550 | H17: =E17+F17+G17
E18: =D18*550 | H18: =E18+F18+G18
E19: =D19*550 | H19: =E19+F19+G19
E20: =D20*550 | H20: =E20+F20+G20
E21: =D21*550 | H21: =E21+F21+G21
E22: =D22*550 | H22: =E22+F22+G22
E23: =D23*550 | H23: =E23+F23+G23
E24: =D24*550 | H24: =E24+F24+G24
E25: =D25*550 | H25: =E25+F25+G25
E26: =D26*550 | H26: =E26+F26+G26
... E44: =D44*550 | H44: =E44+F44+G44
G45: LABOR | H45: =SUM(E15:E44)
G46: VAT 12% | H46: =(H45*12%)
G47: MATERIALS | H47: =SUM(G15:G44)
G48: PARTS | H48: =SUM(F15:F44)
G49: TOTAL | H49: =SUM(H45:H48)
A54: TERMS & CONDITIONS
A55: 1. This quotation is valid only for 15 days from the date of issuance.
A56: 2.The details of the estimate provided above are based on our first inspection and do not constitute a guarantee that no further work/parts will be required. The total bill of work will be per the details available on completion of work. Other terms and conditions as applicable.
A58: 3. Under certain circumstances, Hontech shall not be responsible for any loss or damage to the vehicle including article/s left therein while it is in the premise. Failure to claim your vehicle within the prescribed period shall bear a corresponding storage fee.
A59: 4. To avail of the warranty given for material, parts, and service, owner supplied is discouraged, otherwise a surcharge of 25% of the price of item/s is automatically applied. The price of the item/s shall be the current price of Hontech Auto Center, Inc.
A61: Prepared by: | F61: Approved by:
A63: SERVICE ADVISOR | F63: GENERAL MANAGER / AUTHORIZED OFFICER
A64: I hereby authorize the above repair work listed in accordance with our agreed discussion or with my authorized representative.
C65: =B10
A66: Customer Name and Signature
A67: THANK YOU FOR TRUSTING HONTECH AUTO CENTER, INC!

Sheet Quotation_No 2
H1: Form 2/3
G2: QUOTATION NO.
A3: "Building Trust"
A4: Hontech Auto Center
A5: 70 Bayan Bayanan Ave cor Narra St. | G5: DATE:
A6: Marikina Heights, Marikina City | G6: JOB ORDER NO.: | H6: =Job_Order!K2
A7: fb.com/hontechautocenter | G7: PROMISED DATE:
A8: =Job_Order!B8
A9: CUSTOMER DETAILS
A10: Name: | B10: =Job_Order!C10 | F10: Plate No: | G10: =Job_Order!K10
A11: Address: | B11: =Job_Order!C11 | F11: Year/Model: | G11: =Job_Order!H10
A12: Contact No: | B12: =Job_Order!C12 | F12: Color: | G12: =Job_Order!K13
A14: PARTS/MATERIAL | C14: QTY | D14: FRT | E14: LABOR | F14: PARTS | G14: MATERALS | H14: AMOUNT
E15: =D15*550 | H15: =E15+F15+G15
E16: =D16*550 | H16: =E16+F16+G16
E17: =D17*550 | H17: =E17+F17+G17
E18: =D18*550 | H18: =E18+F18+G18
E19: =D19*550 | H19: =E19+F19+G19
E20: =D20*550 | H20: =E20+F20+G20
E21: =D21*550 | H21: =E21+F21+G21
E22: =D22*550 | H22: =E22+F22+G22
E23: =D23*550 | H23: =E23+F23+G23
E24: =D24*550 | H24: =E24+F24+G24
E25: =D25*550 | H25: =E25+F25+G25
E26: =D26*550 | H26: =E26+F26+G26
... E44: =D44*550 | H44: =E44+F44+G44
G45: LABOR | H45: =SUM(E15:E44)
G46: VAT 12% | H46: =(H45*12%)
G47: MATERIALS | H47: =SUM(G15:G44)
G48: PARTS | H48: =SUM(F15:F44)
G49: TOTAL | H49: =SUM(H45:H48)
A54: TERMS & CONDITIONS
A55: 1. This quotation is valid only for 15 days from the date of issuance.
A56: 2.The details of the estimate provided above are based on our first inspection and do not constitute a guarantee that no further work/parts will be required. The total bill of work will be per the details available on completion of work. Other terms and conditions as applicable.
A58: 3. Under certain circumstances, Hontech shall not be responsible for any loss or damage to the vehicle including article/s left therein while it is in the premise. Failure to claim your vehicle within the prescribed period shall bear a corresponding storage fee.
A59: 4. To avail of the warranty given for material, parts, and service, owner supplied is discouraged, otherwise a surcharge of 25% of the price of item/s is automatically applied. The price of the item/s shall be the current price of Hontech Auto Center, Inc.
A61: Prepared by: | F61: Approved by:
A63: SERVICE ADVISOR | F63: GENERAL MANAGER / AUTHORIZED OFFICER
A64: I hereby authorize the above repair work listed in accordance with our agreed discussion or with my authorized representative.
C65: =B10
A66: Customer Name and Signature
A67: THANK YOU FOR TRUSTING HONTECH AUTO CENTER, INC!

Sheet Quotation_No 3
H1: Form 2/3
G2: QUOTATION NO.
A3: "Building Trust"
A4: Hontech Auto Center
A5: 70 Bayan Bayanan Ave cor Narra St. | G5: DATE:
A6: Marikina Heights, Marikina City | G6: JOB ORDER NO.: | H6: =Job_Order!K2
A7: fb.com/hontechautocenter | G7: PROMISED DATE:
A8: =Job_Order!B8
A9: CUSTOMER DETAILS
A10: Name: | B10: =Job_Order!C10 | F10: Plate No: | G10: =Job_Order!K10
A11: Address: | B11: =Job_Order!C11 | F11: Year/Model: | G11: =Job_Order!H10
A12: Contact No: | B12: =Job_Order!C12 | F12: Color: | G12: =Job_Order!K13
A14: PARTS/MATERIAL | C14: QTY | D14: FRT | E14: LABOR | F14: PARTS | G14: MATERALS | H14: AMOUNT
E15: =D15*550 | H15: =E15+F15+G15
E16: =D16*550 | H16: =E16+F16+G16
E17: =D17*550 | H17: =E17+F17+G17
E18: =D18*550 | H18: =E18+F18+G18
E19: =D19*550 | H19: =E19+F19+G19
E20: =D20*550 | H20: =E20+F20+G20
E21: =D21*550 | H21: =E21+F21+G21
E22: =D22*550 | H22: =E22+F22+G22
E23: =D23*550 | H23: =E23+F23+G23
E24: =D24*550 | H24: =E24+F24+G24
E25: =D25*550 | H25: =E25+F25+G25
E26: =D26*550 | H26: =E26+F26+G26
... E44: =D44*550 | H44: =E44+F44+G44
G45: LABOR | H45: =SUM(E15:E44)
G46: VAT 12% | H46: =(H45*12%)
G47: MATERIALS | H47: =SUM(G15:G44)
G48: PARTS | H48: =SUM(F15:F44)
G49: TOTAL | H49: =SUM(H45:H48)
A54: TERMS & CONDITIONS
A55: 1. This quotation is valid only for 15 days from the date of issuance.
A56: 2.The details of the estimate provided above are based on our first inspection and do not constitute a guarantee that no further work/parts will be required. The total bill of work will be per the details available on completion of work. Other terms and conditions as applicable.
A58: 3. Under certain circumstances, Hontech shall not be responsible for any loss or damage to the vehicle including article/s left therein while it is in the premise. Failure to claim your vehicle within the prescribed period shall bear a corresponding storage fee.
A59: 4. To avail of the warranty given for material, parts, and service, owner supplied is discouraged, otherwise a surcharge of 25% of the price of item/s is automatically applied. The price of the item/s shall be the current price of Hontech Auto Center, Inc.
A61: Prepared by: | F61: Approved by:
A63: SERVICE ADVISOR | F63: GENERAL MANAGER / AUTHORIZED OFFICER
A64: I hereby authorize the above repair work listed in accordance with our agreed discussion or with my authorized representative.
C65: =B10
A66: Customer Name and Signature
A67: THANK YOU FOR TRUSTING HONTECH AUTO CENTER, INC!

Sheet Billing_No 1
H1: Form 3/3
G2: BILLING NO.
A3: "Building Trust"
A4: Hontech Auto Center
A5: 70 Bayan Bayanan Ave cor Narra St. | G5: DATE:
A6: Marikina Heights, Marikina City | G6: JOB ORDER NO.: | H6: =Job_Order!K2
A7: fb.com/hontechautocenter | G7: QUOTATION NO.: | H7: ='Quotation_No 1'!H2
A8: =Job_Order!B8
A9: CUSTOMER DETAILS
A10: Name : | B10: =Job_Order!C10 | F10: Plate No: | G10: =Job_Order!K10
A11: Address : | B11: =Job_Order!C11 | F11: Model/Year: | G11: =Job_Order!H10
A12: Contact No: | B12: =Job_Order!C12 | F12: Color: | G12: =Job_Order!K13
A13: E-Mail Add : | B13: =Job_Order!C13 | F13: Km Reading: | G13: =Job_Order!H11
A14: This is to bill you in the amount of | C14: =H57 | D14: with the following details described below:
A16: PARTS/MATERIAL | C16: QTY | D16: FRT | E16: LABOR | F16: PARTS | G16: MATERALS | H16: AMOUNT
E17: =D17*550 | H17: =G17+F17+E17
E18: =D18*550 | H18: =E18+F18+G18
E19: =D19*550 | H19: =E19+F19+G19
E20: =D20*550 | H20: =E20+F20+G20
E21: =D21*550 | H21: =E21+F21+G21
E22: =D22*550 | H22: =E22+F22+G22
E23: =D23*550 | H23: =E23+F23+G23
E24: =D24*550 | H24: =E24+F24+G24
E25: =D25*550 | H25: =E25+F25+G25
E26: =D26*550 | H26: =E26+F26+G26
E27: =D27*550 | H27: =E27+F27+G27
E28: =D28*550 | H28: =E28+F28+G28
E29: =D29*550 | H29: =E29+F29+G29
... E52: =D52*550 | H52: =E52+F52+G52
G53: LABOR | H53: =SUM(E17:E52)
A54: TERMS & CONDITIONS | G54: VAT 12% | H54: =(H53*12%)
A55: Failure to claim vehicle within the prescribed period shall bear a corresponding storage fee. Replaced items/parts/materials from the vehicle within 30 days shall be disposed of without prior notice. | G55: MATERIALS | H55: =SUM(G17:G52)
G56: PARTS | H56: =SUM(F17:F52)
G57: TOTAL | H57: =SUM(H53:H56)
A58: HONTECH MANGEMENT:
A60: Service Advisor
A62: Thank you for trusting us!

Sheet Billing_No 2
H1: Form 3/3
G2: BILLING NO.
A3: "Building Trust"
A4: Hontech Auto Center
A5: 70 Bayan Bayanan Ave cor Narra St. | G5: DATE:
A6: Marikina Heights, Marikina City | G6: JOB ORDER NO.: | H6: =Job_Order!K2
A7: fb.com/hontechautocenter | G7: QUOTATION NO.: | H7: ='Quotation_No 1'!H2
A8: =Job_Order!B8
A9: CUSTOMER DETAILS
A10: Name : | B10: =Job_Order!C10 | F10: Plate No: | G10: =Job_Order!K10
A11: Address : | B11: =Job_Order!C11 | F11: Model/Year: | G11: =Job_Order!H10
A12: Contact No: | B12: =Job_Order!C12 | F12: Color: | G12: =Job_Order!K13
A13: E-Mail Add : | B13: =Job_Order!C13 | F13: Km Reading: | G13: =Job_Order!H11
A14: This is to bill you in the amount of | C14: =H57 | D14: with the following details described below:
A16: PARTS/MATERIAL | C16: QTY | D16: FRT | E16: LABOR | F16: PARTS | G16: MATERALS | H16: AMOUNT
E17: =D17*550 | H17: =G17+F17+E17
E18: =D18*550 | H18: =E18+F18+G18
E19: =D19*550 | H19: =E19+F19+G19
E20: =D20*550 | H20: =E20+F20+G20
E21: =D21*550 | H21: =E21+F21+G21
E22: =D22*550 | H22: =E22+F22+G22
E23: =D23*550 | H23: =E23+F23+G23
E24: =D24*550 | H24: =E24+F24+G24
E25: =D25*550 | H25: =E25+F25+G25
E26: =D26*550 | H26: =E26+F26+G26
E27: =D27*550 | H27: =E27+F27+G27
E28: =D28*550 | H28: =E28+F28+G28
E29: =D29*550 | H29: =E29+F29+G29
... E52: =D52*550 | H52: =E52+F52+G52
G53: LABOR | H53: =SUM(E17:E52)
A54: TERMS & CONDITIONS | G54: VAT 12% | H54: =(H53*12%)
A55: Failure to claim vehicle within the prescribed period shall bear a corresponding storage fee. Replaced items/parts/materials from the vehicle within 30 days shall be disposed of without prior notice. | G55: MATERIALS | H55: =SUM(G17:G52)
G56: PARTS | H56: =SUM(F17:F52)
G57: TOTAL | H57: =SUM(H53:H56)
A58: HONTECH MANGEMENT:
A60: Service Advisor
A62: Thank you for trusting us!

Sheet CheckList_Result
B2: CUSTOMER NAME | C2: =Job_Order!C10 | Y2: DATE | AD2: =Job_Order!K5
B3: PLATE NUMBER | C3: =Job_Order!K10 | M3: CHECKLIST RESULT
B4: VEHICLE YEAR MODEL | C4: =Job_Order!H10 | M4: FUEL LEVEL: | Y4: E | AB4: 1/4 | AF4: 1/2 | AH4: 3/4 | AL4: F
D6: Satisfactory | G6: May Require Future Attention | R6: Requires Immediate Attention
B8: Interior/Exterior | M8: Tire Condition
B9: Headlights (check high and low beams)/Taillights/Brake lights/Hazard warning lights/Turn signals/Exterior lamps | M9: Left Front | AI9: Right Front
Q10: Wear pattern | AC10: Wear pattern
B11: Interior light
Q12: Tire tread | W12: 32nds | Y12: Tire tread | AG12: 32nds
B13: Windshield washer spray/Wiper operation/Wiper blades/ Windshield condition
M14: Left Rear | AI14: Right Rear
Q15: Wear pattern | AC15: Wear pattern
B16: Parking brake
Q17: Tire tread | W17: 32nds | Y17: Tire tread | AG17: 32nds
B18: Horn operation
M19: Spare
B20: Clutch operation (if applicable)
Q21: Wear pattern | Y21: Front tire inflation set to | AM21: psi
B22: Micron cabin filter**
Q23: Tire tread | W23: 32nds | Y23: Rear tire inflation set to | AM23: psi
B26: Battery Performance (see attached ED-18 printout)
M27: Brake Condition
B28: Good
M29: Left Front | AI29: Right Front
B30: Replace
U31: mms | AE31: mms
M33: Left Rear | AI33: Right Rear
B34: Under Hood
U35: mms | AE35: mms
B36: Check fluid levels: Oil/Coolant/Power steering fluid/Brake fluid*/Windshield washer fluid/Automatic transmission fluid
M37: Brakes not inspected on this visit
B40: Air filter condition**
M41: Please Indicate Areas of External Damage or Wear
B42: External drive belts and radiator hoses
B44: Hydraulic clutch reservoir fluid (M/T vehicles)
B45: Under Vehicle
B46: Brake lines/Hoses/Parking brake cable
B47: Shock absorbers/Struts/Suspension/Tie rod ends and boots/Steering gear and dust seals
B48: Exhaust system
B49: Engine oil and/or fluid leaks
B50: Drive shaft boots/Constant velocity boots and bands
B52: Comments
M59: *Note: Brake fluid NOT filled – fluid level indicate pad wear
M61: **Refer to maintenance schedule
B63: TECHNICIAN NAME: | M63: =Job_Order!C10
M64: CUSTOMER SIGNATURE
